{"index.md":"Bn5wg1vv","lattice_contents.md":"BqYLvuG2","solidity_solidity_1.md":"xWkifPco","cpp_project_list.md":"JsQMWxbM","view.md":"BdPKRi0o","public_z_live2d_banniang_live2d-widget-models_live2d-widget-model-asuna_asuna_readme.md":"DrOkcL3f","lattice_lattice_1.md":"zNfVNz5v","rdp.md":"DvleoDk3","lattice_lattice_2.md":"DT-XH2IQ","vscode_customize.md":"CIPIjc5M","cpp_cpp_1.md":"CG_cfk__","cpp_cpp_3.md":"Bj1Y6kmE","cpp_cpp_2.md":"DA7fCS4V","css.md":"JUk7jTqT","lattice_lattice_3.md":"T6Tu4BKv"}
